README.md
pyxcc-0.1.1.dist-info/METADATA
pyxcc-0.1.1.dist-info/WHEEL
pyxcc.libs/libgcc_s-39080030.so.1
pyxcc/__init__.py
pyxcc/__init__.pyi
pyxcc/py.typed
pyxcc/pyxcc.abi3.so
pyxcc-0.1.1.dist-info/RECORD
