Metadata-Version: 2.4
Name: pyxcc
Version: 0.1.1
Summary: Rust implementation of eXact Cover with Colors algorithm using Donald Knuth's Dancing Cells data structure
Keywords: algorithm,exact-cover,knuth,dancing-links,constraint-satisfaction
License: Apache-2.0 OR MIT
Requires-Python: >=3.9
Project-URL: Homepage, https://github.com/1Juhler-jdj/pyxcc
Project-URL: Repository, https://github.com/1Juhler-jdj/pyxcc
